splashlab/__init__.py
splashlab/computer_vision/__init__.py
splashlab/computer_vision/image_util.py
splashlab/data_management/experiment.py
splashlab/dimensional_analysis/__init__.py
splashlab/dimensional_analysis/convert.py
splashlab/dimensional_analysis/data_reader.py
splashlab/dimensional_analysis/group_of_parameter.py
splashlab/dimensional_analysis/parameter.py
splashlab/dimensional_analysis/unit.py
splashlab/dimensional_analysis/unit_dataframe.py
splashlab/dimensional_analysis/util.py
splashlab-0.1.3.dist-info/LICENSE
splashlab-0.1.3.dist-info/METADATA
splashlab-0.1.3.dist-info/WHEEL
splashlab-0.1.3.dist-info/top_level.txt
splashlab-0.1.3.dist-info/RECORD
