Metadata-Version: 2.1
Name: splashlab
Version: 0.1.3
Summary: A package for fluid mechanic experimentalists
Home-page: https://github.com/FluidsLab/SplashLab
Download-URL: https://github.com/FluidsLab/SplashLab/archive/refs/tags/v0.0.8.tar.gz
Author: Spencer Truman
Author-email: trumans24@gmail.com
License: MIT
Keywords: Fluid Dynamics,Experiment
Classifier: Development Status :: 3 - Alpha
Classifier: Intended Audience :: Developers
Classifier: Topic :: Software Development :: Build Tools
Classifier: License :: OSI Approved :: MIT License
Classifier: Programming Language :: Python :: 3
Classifier: Programming Language :: Python :: 3.8
License-File: LICENSE
Requires-Dist: numpy
Requires-Dist: pandas
Requires-Dist: sympy
Requires-Dist: matplotlib
Requires-Dist: opencv-python
